embaas/__init__.py
embaas/client.py
embaas/core/__init__.py
embaas/core/datetime_utils.py
embaas/core/jsonable_encoder.py
embaas/core/remove_none_from_headers.py
embaas/errors/__init__.py
embaas/errors/api_error.py
embaas/errors/unprocessable_entity_error.py
embaas/types/__init__.py
embaas/types/chunk_splitter.py
embaas/types/document_byte_text_extraction_response.py
embaas/types/document_chunk.py
embaas/types/document_extraction_response.py
embaas/types/document_extraction_response_with_embeddings.py
embaas/types/document_extraction_result.py
embaas/types/document_file_text_extraction_response.py
embaas/types/document_usage.py
embaas/types/document_with_embeddings_usage.py
embaas/types/embedding.py
embaas/types/embeddings_response.py
embaas/types/http_validation_error.py
embaas/types/usage.py
embaas/types/validation_error.py
embaas/types/validation_error_loc_item.py
embaas/types/whisper_response.py
embaas/types/whisper_result.py
embaas/types/whisper_usage.py
embaas/utils.py
embaas-0.0.12.dist-info/LICENSE
embaas-0.0.12.dist-info/METADATA
embaas-0.0.12.dist-info/WHEEL
embaas-0.0.12.dist-info/RECORD
